django_sio-0.1.0.dist-info/licenses/LICENSE
sio/__init__.py
sio/consumer.py
sio/engineio/__init__.py
sio/engineio/app.py
sio/engineio/constants.py
sio/engineio/packets.py
sio/engineio/polling.py
sio/engineio/session.py
sio/engineio/utils.py
sio/engineio/websocket.py
sio/socketio/__init__.py
sio/socketio/constants.py
sio/socketio/protocol.py
sio/socketio/server.py
sio/socketio/socket.py
django_sio-0.1.0.dist-info/METADATA
django_sio-0.1.0.dist-info/WHEEL
django_sio-0.1.0.dist-info/top_level.txt
django_sio-0.1.0.dist-info/RECORD
