Metadata-Version: 2.4
Name: django-sio
Version: 0.1.0
Summary: SocketIO for Django
Requires-Python: >=3.8
License-File: LICENSE
Requires-Dist: channels>=4.0
Requires-Dist: django>=4.2
Dynamic: license-file
